{
    "crawler_frequency": 30,
    "crawler_servers": ["KS-2A"],
    "crawler_zones": ["bhs", "centralEurope", "fr", "gra", "hardzone", "northAmerica", "rbx", "rbx-hz", "sbg", "westernEurope"],
    "irc_channels": ["#arab"],
    "irc_gecos": "Kimsufi bot",
    "irc_nick": "ksbot",
    "irc_server_hname": "10.128.0.2",
    "irc_server_port": 6667,
    "irc_user": "ksbot",
    "ks_datacenters": {"bhs":"Beauharnois, Canada (Americas)","gra":"Gravelines, France","rbx":"Roubaix, France (Western Europe)","sbg":"Strasbourg, France (Central Europe)","centralEurope":"Central Europe","northAmerica":"North America","westernEurope":"Western Europe","hardzone":"hardzone","rbx-hz":"Roubaix, France (Western Europe) (hardzone)"},
    "ks_server_types": {"160sk1":"KS-1","160sk2":"KS-2A","160sk21":"KS-2B","160sk22":"KS-2C","160sk23":"KS-2D","161sk2":"KS-2E","160sk3":"KS-3A","160sk31":"KS-3B","160sk32":"KS-3C","160sk4":"KS-4A","160sk41":"KS-4B","160sk42":"KS-4C","160sk5":"KS-5","160sk6":"KS-6"},
    "ks_url": "https://ws.ovh.com/dedicated/r2/ws.dispatcher/getAvailability2"
}
